{
  "sicherheit": {
    "label": "Sicherheit",
    "required": [
      { "value": "unterrichtung-34a", "label": "Unterrichtung §34a" }
    ],
    "optional": [
      { "value": "bewacher-id", "label": "Bewacher-ID" },
      { "value": "deeskalation", "label": "Deeskalation" },
      { "value": "event-erfahrung", "label": "Event-Erfahrung" },
      { "value": "erste-hilfe", "label": "Erste Hilfe" },
      { "value": "handfunkgeraet", "label": "Funkgerät" },
      { "value": "lageeinschaetzung", "label": "Lageeinschätzung" },
      { "value": "nachtarbeit", "label": "Nachtarbeit" },
      { "value": "objektschutz", "label": "Objektschutz" }
    ]
  },
  "gastronomie": {
    "label": "Gastronomie",
    "required": [],
    "optional": [
      { "value": "buffet", "label": "Buffet" },
      { "value": "cocktail-kenntnisse", "label": "Cocktail-Kenntnisse" },
      { "value": "fruehstueck-service", "label": "Frühstücksservice" },
      { "value": "kassieren", "label": "Kassieren" },
      { "value": "service-erfahrung", "label": "Service-Erfahrung" },
      { "value": "tablett-tragen", "label": "Tablett tragen" },
      { "value": "zapfen", "label": "Zapfen" }
    ]
  },
  "lieferservice": {
    "label": "Lieferservice",
    "required": [],
    "optional": [
      { "value": "auto", "label": "PKW" },
      { "value": "fahrrad", "label": "Fahrrad" },
      { "value": "kundenkontakt", "label": "Kundenkontakt" },
      { "value": "motorroller", "label": "Motorroller" },
      { "value": "navigation", "label": "Navigation" }
    ]
  },
  "lager_logistik": {
    "label": "Lager & Logistik",
    "required": [],
    "optional": [
      { "value": "handscanner", "label": "Handscanner" },
      { "value": "hubwagen", "label": "Hubwagen" },
      { "value": "kommissionieren", "label": "Kommissionieren" },
      { "value": "pick-pack", "label": "Pick & Pack" },
      { "value": "regalpflege", "label": "Regalpflege" },
      { "value": "staplerschein", "label": "Staplerschein" },
      { "value": "verpacken", "label": "Verpacken" }
    ]
  },
  "einzelhandel": {
    "label": "Einzelhandel",
    "required": [],
    "optional": [
      { "value": "etikettieren", "label": "Etikettieren" },
      { "value": "kassieren", "label": "Kassieren" },
      { "value": "kundenberatung", "label": "Kundenberatung" },
      { "value": "lagererfahrung", "label": "Lagererfahrung" },
      { "value": "umgang-mit-scanner", "label": "Scanner bedienen" },
      { "value": "warenverraeumung", "label": "Waren verräumen" }
    ]
  },
  "event_messe": {
    "label": "Event & Messe",
    "required": [],
    "optional": [
      { "value": "abbau", "label": "Abbau" },
      { "value": "aufbau", "label": "Aufbau" },
      { "value": "gastbetreuung", "label": "Gastbetreuung" },
      { "value": "kassenkenntnisse", "label": "Kassenkenntnisse" },
      { "value": "promo-erfahrung", "label": "Promo-Erfahrung" },
      { "value": "ticketing", "label": "Ticketing" }
    ]
  },
  "reinigung": {
    "label": "Reinigung",
    "required": [],
    "optional": [
      { "value": "buero-reinigung", "label": "Büroreinigung" },
      { "value": "fensterreinigung", "label": "Fensterreinigung" },
      { "value": "grundreinigung", "label": "Grundreinigung" },
      { "value": "hotelreinigung", "label": "Hotelreinigung" },
      { "value": "schluesseluebergabe", "label": "Schlüsselübergabe" }
    ]
  },
  "bau_helfer": {
    "label": "Bauhelfer",
    "required": [],
    "optional": [
      { "value": "abbruch", "label": "Abbrucharbeiten" },
      { "value": "leiterkenntnisse", "label": "Leiterkenntnisse" },
      { "value": "materialtransport", "label": "Materialtransport" },
      { "value": "schutzkleidung", "label": "Schutzkleidung" },
      { "value": "schubkarre", "label": "Schubkarre" },
      { "value": "werkzeug-kenntnisse", "label": "Werkzeugkenntnisse" }
    ]
  },
  "haus_garten": {
    "label": "Haus & Garten",
    "required": [],
    "optional": [
      { "value": "bewaesserung", "label": "Bewässerung" },
      { "value": "gartenpflege", "label": "Gartenpflege" },
      { "value": "heckenschneiden", "label": "Heckenschneiden" },
      { "value": "kleinreparaturen", "label": "Kleinreparaturen" },
      { "value": "rasenmaehen", "label": "Rasenmähen" },
      { "value": "werkzeug-kenntnisse", "label": "Werkzeugkenntnisse" }
    ]
  },
  "babysitting_kinder": {
    "label": "Babysitting & Kinder",
    "required": [],
    "optional": [
      { "value": "erfahrung-babysitting", "label": "Erfahrung Babysitting" },
      { "value": "erste-hilfe-kind", "label": "Erste Hilfe Kind" },
      { "value": "hausaufgaben", "label": "Hausaufgabenhilfe" },
      { "value": "haushalt-light", "label": "Haushalt (leicht)" }
    ]
  },
  "kleinstreparaturen_handwerk": {
    "label": "Kleinstreparaturen",
    "required": [],
    "optional": [
      { "value": "bohren", "label": "Bohren" },
      { "value": "montage", "label": "Montage" },
      { "value": "moebelaufbau", "label": "Möbelaufbau" },
      { "value": "schrauben", "label": "Schrauben" },
      { "value": "werkzeug-kenntnisse", "label": "Werkzeugkenntnisse" }
    ]
  },
  "haustiere": {
    "label": "Haustiere",
    "required": [],
    "optional": [
      { "value": "gassiservice", "label": "Gassiservice" },
      { "value": "hundeerfahrung", "label": "Hundeerfahrung" },
      { "value": "katzenpflege", "label": "Katzenpflege" },
      { "value": "tierbetreuung", "label": "Tierbetreuung" },
      { "value": "tiermedizin-basic", "label": "Tiermedizin Grundlagen" }
    ]
  },
  "umzug_transport": {
    "label": "Umzug & Transport",
    "required": [],
    "optional": [
      { "value": "demontage", "label": "Demontage" },
      { "value": "montage", "label": "Montage" },
      { "value": "schwerlast", "label": "Schwerlast" },
      { "value": "tragen", "label": "Tragen" },
      { "value": "verpacken", "label": "Verpacken" }
    ]
  },
  "buero_service": {
    "label": "Büro & Service",
    "required": [],
    "optional": [
      { "value": "crm", "label": "CRM" },
      { "value": "datenpflege", "label": "Datenpflege" },
      { "value": "kassensysteme", "label": "Kassensysteme" },
      { "value": "kundenkontakt", "label": "Kundenkontakt" },
      { "value": "postbearbeitung", "label": "Postbearbeitung" },
      { "value": "telefonie", "label": "Telefonie" }
    ]
  },
  "it_support": {
    "label": "IT Support",
    "required": [],
    "optional": [
      { "value": "drucker", "label": "Drucker" },
      { "value": "hardware-basic", "label": "Hardware Basics" },
      { "value": "macos", "label": "macOS" },
      { "value": "netzwerk-basic", "label": "Netzwerk Basics" },
      { "value": "software-installation", "label": "Software Installation" },
      { "value": "support-erfahrung", "label": "Support Erfahrung" },
      { "value": "windows", "label": "Windows" }
    ]
  },
  "foto_video": {
    "label": "Foto & Video",
    "required": [],
    "optional": [
      { "value": "bilder-bearbeiten", "label": "Bildbearbeitung" },
      { "value": "kamera-bedienung", "label": "Kamera bedienen" },
      { "value": "licht", "label": "Licht" },
      { "value": "schnitt", "label": "Videoschnitt" },
      { "value": "social-media", "label": "Social Media" },
      { "value": "ton", "label": "Ton" }
    ]
  },
  "nachhilfe": {
    "label": "Nachhilfe",
    "required": [],
    "optional": [
      { "value": "deutsch", "label": "Deutsch" },
      { "value": "englisch", "label": "Englisch" },
      { "value": "hausaufgabenbetreuung", "label": "Hausaufgabenbetreuung" },
      { "value": "mathe", "label": "Mathe" },
      { "value": "naturwissenschaften", "label": "Naturwissenschaften" },
      { "value": "unterrichtserfahrung", "label": "Unterrichtserfahrung" }
    ]
  },
  "fahrdienst": {
    "label": "Fahrdienst",
    "required": [
      { "value": "fuehrerschein-b", "label": "Führerschein (Klasse B)" }
    ],
    "optional": [
      { "value": "fahrzeugpflege", "label": "Fahrzeugpflege" },
      { "value": "kundenkontakt", "label": "Kundenkontakt" },
      { "value": "navigation", "label": "Navigation" },
      { "value": "personenbefoerderung", "label": "Personenbeförderung" }
    ]
  },
  "hauswirtschaft": {
    "label": "Hauswirtschaft",
    "required": [],
    "optional": [
      { "value": "betreuung-basic", "label": "Betreuung (Basic)" },
      { "value": "buegeln", "label": "Bügeln" },
      { "value": "einkaufen", "label": "Einkaufen" },
      { "value": "kochen", "label": "Kochen" },
      { "value": "waschen", "label": "Waschen" }
    ]
  }
}
